ormex/__init__.py
ormex/aggregations/__init__.py
ormex/aggregations/group_concat/__init__.py
ormex/aggregations/group_concat/base.py
ormex/aggregations/group_concat/django_gte_1_10.py
ormex/aggregations/group_concat/django_lte_1_9.py
ormex/tests/__init__.py
ormex/tests/base.py
ormex/tests/helpers.py
ormex/tests/test_aggregations.py
django_ormex-0.2.1.dist-info/LICENSE_GPL2.0.txt
django_ormex-0.2.1.dist-info/LICENSE_LGPL_2.1.txt
django_ormex-0.2.1.dist-info/METADATA
django_ormex-0.2.1.dist-info/WHEEL
django_ormex-0.2.1.dist-info/top_level.txt
django_ormex-0.2.1.dist-info/RECORD
